zillow_rapidapi_client/__init__.py
zillow_rapidapi_client/_hooks/__init__.py
zillow_rapidapi_client/_hooks/registration.py
zillow_rapidapi_client/_hooks/sdkhooks.py
zillow_rapidapi_client/_hooks/types.py
zillow_rapidapi_client/_version.py
zillow_rapidapi_client/basesdk.py
zillow_rapidapi_client/httpclient.py
zillow_rapidapi_client/models/__init__.py
zillow_rapidapi_client/models/apierror.py
zillow_rapidapi_client/models/property.py
zillow_rapidapi_client/models/propertyextendedsearchop.py
zillow_rapidapi_client/models/propertysearchresponse.py
zillow_rapidapi_client/properties.py
zillow_rapidapi_client/py.typed
zillow_rapidapi_client/sdk.py
zillow_rapidapi_client/sdkconfiguration.py
zillow_rapidapi_client/types/__init__.py
zillow_rapidapi_client/types/basemodel.py
zillow_rapidapi_client/utils/__init__.py
zillow_rapidapi_client/utils/annotations.py
zillow_rapidapi_client/utils/enums.py
zillow_rapidapi_client/utils/eventstreaming.py
zillow_rapidapi_client/utils/forms.py
zillow_rapidapi_client/utils/headers.py
zillow_rapidapi_client/utils/logger.py
zillow_rapidapi_client/utils/metadata.py
zillow_rapidapi_client/utils/queryparams.py
zillow_rapidapi_client/utils/requestbodies.py
zillow_rapidapi_client/utils/retries.py
zillow_rapidapi_client/utils/security.py
zillow_rapidapi_client/utils/serializers.py
zillow_rapidapi_client/utils/url.py
zillow_rapidapi_client/utils/values.py
zillow_rapidapi_client-0.1.4.dist-info/METADATA
zillow_rapidapi_client-0.1.4.dist-info/WHEEL
zillow_rapidapi_client-0.1.4.dist-info/RECORD
